odoo/addons/l10n_es_irnr_sii/README.rst
odoo/addons/l10n_es_irnr_sii/__init__.py
odoo/addons/l10n_es_irnr_sii/__manifest__.py
odoo/addons/l10n_es_irnr_sii/i18n/l10n_es_irnr_sii.pot
odoo/addons/l10n_es_irnr_sii/readme/CONFIGURE.rst
odoo/addons/l10n_es_irnr_sii/readme/CONTRIBUTORS.rst
odoo/addons/l10n_es_irnr_sii/readme/DESCRIPTION.rst
odoo/addons/l10n_es_irnr_sii/readme/ROADMAP.rst
odoo/addons/l10n_es_irnr_sii/readme/USAGE.rst
odoo/addons/l10n_es_irnr_sii/static/description/icon.png
odoo/addons/l10n_es_irnr_sii/static/description/index.html
odoo_addon_l10n_es_irnr_sii-16.0.1.1.0.dist-info/METADATA
odoo_addon_l10n_es_irnr_sii-16.0.1.1.0.dist-info/WHEEL
odoo_addon_l10n_es_irnr_sii-16.0.1.1.0.dist-info/top_level.txt
odoo_addon_l10n_es_irnr_sii-16.0.1.1.0.dist-info/RECORD
